factual/__init__.py
factual/f1chexbert.py
factual/f1temporal.py
factual/RaTEScore/__init__.py
factual/RaTEScore/score.py
factual/RaTEScore/scorer.py
factual/RaTEScore/utils.py
factual/green_score/__init__.py
factual/green_score/green.py
factual/green_score/utils.py
nlg/__init__.py
nlg/radevalbertscore.py
nlg/bertscore/__init__.py
nlg/bertscore/bertscore.py
nlg/bleu/__init__.py
nlg/bleu/bleu.py
nlg/bleu/bleu_scorer.py
nlg/rouge/__init__.py
nlg/rouge/rouge.py
pypitest_radeval-0.0.1.dist-info/licenses/LICENSE
tests/__init__.py
tests/test_basics.py
tests/test_details.py
tests/test_f1chexbert.py
tests/test_greenscore.py
tests/test_structeval_parsing.py
pypitest_radeval-0.0.1.dist-info/METADATA
pypitest_radeval-0.0.1.dist-info/WHEEL
pypitest_radeval-0.0.1.dist-info/top_level.txt
pypitest_radeval-0.0.1.dist-info/RECORD
