Metadata-Version: 2.4
Name: pypitest_radeval
Version: 0.0.1
Summary: All-in-one metrics for evaluating AI-generated radiology text
Home-page: https://github.com/jbdel/RadEval
Author: Xi Zhang， auther 1, auther 2
Author-email: xi.zhang@example.com
Maintainer: Xi Zhang, auther1, auther2
Maintainer-email: xi.zhang@example.com
License: MIT
Project-URL: Bug Reports, https://github.com/X-iZhang/pypitest/issues
Project-URL: Source, https://github.com/X-iZhang/pypitest
Project-URL: Documentation, https://github.com/X-iZhang/pypitest/blob/main/README.md
Keywords: radiology,evaluation,natural language processing,radiology report,medical NLP,clinical text generation,LLM,bioNLP,chexbert,radgraph,medical AI
Classifier: Intended Audience :: Science/Research
Classifier: Topic :: Scientific/Engineering
Classifier: License :: OSI Approved :: MIT License
Classifier: Programming Language :: Python :: 3 :: Only
Requires-Python: >=3.9,<=3.12.1
License-File: LICENSE
Requires-Dist: torch<3.0,>=2.2.2
Requires-Dist: transformers>=4.53.1
Requires-Dist: radgraph
Requires-Dist: rouge_score
Requires-Dist: bert-score==0.3.13
Requires-Dist: scikit-learn
Requires-Dist: numpy<2
Requires-Dist: medspacy
Requires-Dist: stanza
Requires-Dist: accelerate==0.30.1
Requires-Dist: pillow==10.3.0
Requires-Dist: sentencepiece==0.2.0
Requires-Dist: sentence-transformers==3.0.1
Requires-Dist: datasets==2.19.0
Requires-Dist: torchvision==0.17.2
Requires-Dist: opencv-python==4.10.0.84
Requires-Dist: scipy
Requires-Dist: matplotlib
Requires-Dist: pandas
Dynamic: author
Dynamic: author-email
Dynamic: classifier
Dynamic: description
Dynamic: description-content-type
Dynamic: home-page
Dynamic: keywords
Dynamic: license
Dynamic: license-file
Dynamic: maintainer
Dynamic: maintainer-email
Dynamic: project-url
Dynamic: requires-dist
Dynamic: requires-python
Dynamic: summary
